[
  {
    "id": "706501100000",
    "name": "Miobrill Fleckenradierer",
    "categoryCode": "BeSS_0104200301",
    "image": {
      "original": "https://image.migros.ch/original/a2979b7888afd36ce090d4cc0059a4dd7057584b/miobrill-fleckenradierer.jpg"
    },
    "price": 2.5,
    "priceScore": 0.4137931034482759,
    "kcalScore": null,
    "co2Score": 1,
    "totalScore": 0.4137931034482758
  },
  {
    "id": "706503600000",
    "name": "Miobrill Strong Schwämme Synthetisch",
    "categoryCode": "BeSS_0104200301",
    "image": {
      "original": "https://image.migros.ch/original/b994009c823886870018bd6878984b1bbbcaf28b/miobrill-strong-schwaemme-synthetisch.jpg"
    },
    "price": 1.5,
    "priceScore": 0.7586206896551725,
    "kcalScore": null,
    "co2Score": 1,
    "totalScore": 0.7586206896551726
  },
  {
    "id": "706503700000",
    "name": "Miobrill Universal Schwämme Synthetisch",
    "categoryCode": "BeSS_0104200301",
    "image": {
      "original": "https://image.migros.ch/original/ed79ae7ead2fbde6ebcc00be96b7771712491877/miobrill-universal-schwaemme-synthetisch.jpg"
    },
    "price": 2.9,
    "priceScore": 0.27586206896551746,
    "kcalScore": null,
    "co2Score": 1,
    "totalScore": 0.27586206896551735
  },
  {
    "id": "706503800000",
    "name": "Miobrill Soft Schwamm Synthetisch extra gross",
    "categoryCode": "BeSS_0104200301",
    "image": {
      "original": "https://image.migros.ch/original/66c4e6c6db0ca74fd094addb069f4f328cb471a4/miobrill-soft-schwamm-synthetisch-extra-gross.jpg"
    },
    "price": 1.9,
    "priceScore": 0.6206896551724139,
    "kcalScore": null,
    "co2Score": 1,
    "totalScore": 0.6206896551724139
  },
  {
    "id": "706503900000",
    "name": "Miobrill Soft Schwämme Synthetisch",
    "categoryCode": "BeSS_0104200301",
    "image": {
      "original": "https://image.migros.ch/original/3f82452185061fde80f954b44eba63549ba26b30/miobrill-soft-schwaemme-synthetisch.jpg"
    },
    "price": 1.5,
    "priceScore": 0.7586206896551725,
    "kcalScore": null,
    "co2Score": 1,
    "totalScore": 0.7586206896551726
  },
  {
    "id": "706504000000",
    "name": "Miobrill Soft & Dry Schwämme Synthetisch",
    "categoryCode": "BeSS_0104200301",
    "image": {
      "original": "https://image.migros.ch/original/4262372fd1de7a6127344737da76d5a343467688/miobrill-soft-dry-schwaemme-synthetisch.jpg"
    },
    "price": 2.9,
    "priceScore": 0.27586206896551746,
    "kcalScore": null,
    "co2Score": 1,
    "totalScore": 0.27586206896551735
  },
  {
    "id": "706504300000",
    "name": "M-Budget Schwämme",
    "categoryCode": "BeSS_0104200301",
    "image": {
      "original": "https://image.migros.ch/original/0e4ec2174e12513a782dabcad0112f61ea9c02e0/m-budget-schwaemme.jpg"
    },
    "price": 0.8,
    "priceScore": 1,
    "kcalScore": null,
    "co2Score": 1,
    "totalScore": 1
  },
  {
    "id": "706507800000",
    "name": "Miobrill Strong Schwämme",
    "categoryCode": "BeSS_0104200301",
    "image": {
      "original": "https://image.migros.ch/original/c37f32bc889197a16d7590e9cffec0fea7d41f92/miobrill-strong-schwaemme.jpg"
    },
    "price": 1.15,
    "priceScore": 0.8793103448275863,
    "kcalScore": null,
    "co2Score": 1,
    "totalScore": 0.8793103448275863
  },
  {
    "id": "706511200000",
    "name": "Miobrill Pads Strong",
    "categoryCode": "BeSS_0104200301",
    "image": {
      "original": "https://image.migros.ch/original/cf1f4975b1a85ae35d67cb51d613a76c8d0a49d8/miobrill-pads-strong.jpg"
    },
    "price": 1.9,
    "priceScore": 0.6206896551724139,
    "kcalScore": null,
    "co2Score": 1,
    "totalScore": 0.6206896551724139
  },
  {
    "id": "706512000000",
    "name": "Miobrill Strong Schwämme Cellulose",
    "categoryCode": "BeSS_0104200301",
    "image": {
      "original": "https://image.migros.ch/original/22dc7473ee1bee943607692f5e56abc480428b9f/miobrill-strong-schwaemme-cellulose.jpg"
    },
    "price": 2.8,
    "priceScore": 0.3103448275862071,
    "kcalScore": null,
    "co2Score": 1,
    "totalScore": 0.3103448275862071
  },
  {
    "id": "706512500000",
    "name": "Miobrill Polierschwämme Viskose",
    "categoryCode": "BeSS_0104200301",
    "image": {
      "original": "https://image.migros.ch/original/9304b749c9444ca2c83ec3a27a540e12dadd8717/miobrill-polierschwaemme-viskose.jpg"
    },
    "price": 3.7,
    "priceScore": 0,
    "kcalScore": null,
    "co2Score": 1,
    "totalScore": 0
  }
]