{
  "id": "152004900000",
  "language": "de",
  "name": "Sun Queen Max Hav Ananasscheiben",
  "names": {
    "name": "Sun Queen Max Hav Ananasscheiben"
  },
  "slug": "sun-queen-max-hav-ananasscheiben",
  "boss_number": "011111092105",
  "description": {
    "text": "Ananasscheiben in Ananassaft",
    "source": "PIM"
  },
  "status": {
    "id": "available",
    "seasonal": false,
    "pim_status": "03"
  },
  "tags": [
    "source-pim",
    "migipedia",
    "source-qim-origins",
    "validity-range-not-set",
    "source-qim-fooddeclaration",
    "source-qim-nutritionfacts",
    "view-browse-partial",
    "view-browse-all-retailers-partial"
  ],
  "is_variant": false,
  "gtins": [
    "7613312104897"
  ],
  "brand": {
    "id": "178",
    "name": "Sun Queen",
    "slug": "sun-queen",
    "image": {
      "original": "https://image.migros.ch/original/6035c048bc686d3e8e595bd52f53b7732470d741/sun-queen.jpg",
      "stack": "https://image.migros.ch/{stack}/6035c048bc686d3e8e595bd52f53b7732470d741/sun-queen.jpg"
    }
  },
  "labels": [
    {
      "id": "L04",
      "name": "Fairtrade Max Havelaar",
      "slug": "fairtrade-max-havelaar",
      "links": {
        "homepage": {
          "url": "https://www.maxhavelaar.ch",
          "name": "Homepage",
          "type": "info",
          "purchasable": false
        }
      },
      "image": {
        "original": "https://image.migros.ch/original/f3f929f7d307eaefdb78d50c6b493c51b105c9b4/fairtrade-max-havelaar.jpg",
        "stack": "https://image.migros.ch/{stack}/f3f929f7d307eaefdb78d50c6b493c51b105c9b4/fairtrade-max-havelaar.jpg"
      }
    }
  ],
  "categories": [
    {
      "code": "BeSS_01011415",
      "name": "Früchtekonserven",
      "slug": "supermarkt/lebensmittel/pasta-zutaten-konserven/fruechtekonserven",
      "visible": true,
      "parent_code": "BeSS_010114",
      "image": {
        "original": "https://image.migros.ch/original/0ddab8a8d58f3a9713c510b0e506fc69558499b2/fruechtekonserven.jpg",
        "stack": "https://image.migros.ch/{stack}/0ddab8a8d58f3a9713c510b0e506fc69558499b2/fruechtekonserven.jpg"
      },
      "level": 4
    },
    {
      "code": "BeSS_010114",
      "name": "Pasta, Zutaten & Konserven",
      "slug": "supermarkt/lebensmittel/pasta-zutaten-konserven",
      "visible": true,
      "title": "Pasta aus Ihrer Migros: alles rund um Teigwaren",
      "parent_code": "BeSS_0101",
      "image": {
        "original": "https://image.migros.ch/original/6d0964bbb34b8e041ba4d74fc0c90b149907f46a/pasta-zutaten-konserven.jpg",
        "stack": "https://image.migros.ch/{stack}/6d0964bbb34b8e041ba4d74fc0c90b149907f46a/pasta-zutaten-konserven.jpg"
      },
      "level": 3
    },
    {
      "code": "BeSS_0101",
      "name": "Lebensmittel",
      "slug": "supermarkt/lebensmittel",
      "visible": true,
      "title": "Lebensmittel aus Ihrer Migros: hochwertige Produkte, ausgewogener Genuss",
      "parent_code": "BeSS_01",
      "image": {
        "original": "https://image.migros.ch/original/c4c714b236338d5b9a042dd7dd2457b7e8604696/lebensmittel.jpg",
        "stack": "https://image.migros.ch/{stack}/c4c714b236338d5b9a042dd7dd2457b7e8604696/lebensmittel.jpg"
      },
      "level": 2
    },
    {
      "code": "BeSS_01",
      "name": "Supermarkt",
      "slug": "supermarkt",
      "visible": true,
      "parent_code": "root",
      "level": 1
    }
  ],
  "additional_categories": [
    [
      {
        "code": "AMIG_CAT_Fruechte_KonservenEingemachtes_Grundnahrungsmittel",
        "name": "Früchte",
        "slug": "amigos/grundnahrungsmittel/konserven-eingemachtes/fruechte",
        "visible": true,
        "parent_code": "AMIG_CAT_KonservenEingemachtes_Grundnahrungsmittel",
        "level": 4
      },
      {
        "code": "AMIG_CAT_KonservenEingemachtes_Grundnahrungsmittel",
        "name": "Konserven & Eingemachtes",
        "slug": "amigos/grundnahrungsmittel/konserven-eingemachtes",
        "visible": true,
        "parent_code": "AMIG_CAT_Grundnahrungsmittel",
        "level": 3
      },
      {
        "code": "AMIG_CAT_Grundnahrungsmittel",
        "name": "Grundnahrungsmittel",
        "slug": "amigos/grundnahrungsmittel",
        "visible": true,
        "parent_code": "BeSS_96",
        "level": 2
      },
      {
        "code": "BeSS_96",
        "name": "aMigos!",
        "slug": "amigos",
        "visible": true,
        "parent_code": "root",
        "level": 1
      }
    ]
  ],
  "nutrition_facts": {
    "standard": {
      "nutrients": [
        {
          "code": "PIM_NUT_ENERGIE",
          "name": "Energie",
          "pictogram_name": "Energie",
          "category": "BIG9",
          "quantity": 267,
          "nutrition_operator": "=",
          "quantity_unit": "kJ",
          "quantity_alternate": 63,
          "quantity_alternate_unit": "kcal"
        },
        {
          "code": "PIM_NUT_FETT",
          "name": "Fett",
          "pictogram_name": "Fett",
          "category": "BIG9",
          "quantity": 0,
          "nutrition_operator": "=",
          "quantity_unit": "g"
        },
        {
          "code": "PIM_NUT_FETT_GES",
          "name": "davon gesättigte Fettsäuren",
          "pictogram_name": "gesättigte Fettsäuren",
          "category": "BIG9",
          "quantity": 0,
          "nutrition_operator": "=",
          "quantity_unit": "g"
        },
        {
          "code": "PIM_NUT_KOHLENHY",
          "name": "Kohlenhydrate",
          "category": "BIG9",
          "quantity": 15,
          "nutrition_operator": "=",
          "quantity_unit": "g"
        },
        {
          "code": "PIM_NUT_ZUCKER",
          "name": "davon Zucker",
          "pictogram_name": "Zuckerarten",
          "category": "BIG9",
          "quantity": 13,
          "nutrition_operator": "=",
          "quantity_unit": "g"
        },
        {
          "code": "PIM_NUT_GES_BALL",
          "name": "Ballaststoffe",
          "category": "BIG9",
          "quantity": 0.7,
          "nutrition_operator": "=",
          "quantity_unit": "g"
        },
        {
          "code": "PIM_NUT_PROTEINE",
          "name": "Eiweiss",
          "category": "BIG9",
          "quantity": 0.5,
          "nutrition_operator": "<",
          "quantity_unit": "g"
        },
        {
          "code": "PIM_NUT_KOCHSALZ",
          "name": "Salz",
          "pictogram_name": "Salz",
          "category": "BIG9",
          "quantity": 0.01,
          "nutrition_operator": "<",
          "quantity_unit": "g"
        }
      ],
      "base_quantity": 100,
      "base_unit": "g"
    },
    "portion": {
      "nutrients": [
        {
          "code": "PIM_NUT_ENERGIE",
          "name": "Energie",
          "pictogram_name": "Energie",
          "category": "BIG9",
          "quantity": 374,
          "rda_percent": 4,
          "rda_percent_operator": "=",
          "nutrition_operator": "=",
          "quantity_unit": "kJ",
          "quantity_alternate": 88,
          "quantity_alternate_unit": "kcal"
        },
        {
          "code": "PIM_NUT_FETT",
          "name": "Fett",
          "pictogram_name": "Fett",
          "category": "BIG9",
          "quantity": 0,
          "rda_percent": 0,
          "rda_percent_operator": "=",
          "nutrition_operator": "=",
          "quantity_unit": "g"
        },
        {
          "code": "PIM_NUT_FETT_GES",
          "name": "davon gesättigte Fettsäuren",
          "pictogram_name": "gesättigte Fettsäuren",
          "category": "BIG9",
          "quantity": 0,
          "rda_percent": 0,
          "rda_percent_operator": "=",
          "nutrition_operator": "=",
          "quantity_unit": "g"
        },
        {
          "code": "PIM_NUT_KOHLENHY",
          "name": "Kohlenhydrate",
          "category": "BIG9",
          "quantity": 21,
          "rda_percent": 8,
          "rda_percent_operator": "=",
          "nutrition_operator": "=",
          "quantity_unit": "g"
        },
        {
          "code": "PIM_NUT_ZUCKER",
          "name": "davon Zucker",
          "pictogram_name": "Zuckerarten",
          "category": "BIG9",
          "quantity": 18,
          "rda_percent": 20,
          "rda_percent_operator": "=",
          "nutrition_operator": "=",
          "quantity_unit": "g"
        },
        {
          "code": "PIM_NUT_GES_BALL",
          "name": "Ballaststoffe",
          "category": "BIG9",
          "quantity": 1,
          "nutrition_operator": "=",
          "quantity_unit": "g"
        },
        {
          "code": "PIM_NUT_PROTEINE",
          "name": "Eiweiss",
          "category": "BIG9",
          "quantity": 0.5,
          "rda_percent": 1,
          "rda_percent_operator": "=",
          "nutrition_operator": "=",
          "quantity_unit": "g"
        },
        {
          "code": "PIM_NUT_KOCHSALZ",
          "name": "Salz",
          "pictogram_name": "Salz",
          "category": "BIG9",
          "quantity": 0.01,
          "rda_percent": 0.5,
          "rda_percent_operator": "<",
          "nutrition_operator": "<",
          "quantity_unit": "g"
        }
      ],
      "base_description": "4 Scheiben",
      "base_quantity": 136,
      "base_quantity_description": "abgetropft",
      "base_unit": "g",
      "package_type": "Dose",
      "portions_per_package": "2.5",
      "portions_per_package_precision": "="
    }
  },
  "features": [
    {
      "label_code": "MISO_cu_gebindeart",
      "label": "Verpackungsart",
      "values": [
        {
          "value_code": "MISO_cu_gebindeart_dose",
          "value": "Dose"
        }
      ],
      "category_code": "MISO_CLA_LebensmittelGetraenke_Alle",
      "top_fact": false
    },
    {
      "label_code": "MISO_ursprungsland",
      "label": "Ursprungsland",
      "values": [
        {
          "value_code": "MISO_Herkunftsland_Thailand",
          "value": "Thailand"
        }
      ],
      "category_code": "MISO_CLA_ObstFruechte_LebensmittelGetraenke_Alle",
      "top_fact": false
    },
    {
      "label_code": "MISO_formbeschaffenheitvonobst",
      "label": "Form/Beschaffenheit",
      "values": [
        {
          "value_code": "MISO_formbeschaffenheitvonobst_inscheiben",
          "value": "in Scheiben"
        }
      ],
      "category_code": "MISO_CLA_ObstFruechte_LebensmittelGetraenke_Alle",
      "top_fact": false
    },
    {
      "label_code": "MISO_sorte",
      "label": "Sorte",
      "values": [
        {
          "value_code": "MISO_sorte_ananas",
          "value": "Ananas"
        }
      ],
      "category_code": "MISO_CLA_bearbeiteteshaltbaresObstFruechte_ObstFruechte_LebensmittelGetraenke_Alle",
      "top_fact": false
    }
  ],
  "general_information": [
    {
      "label": "Produktionshinweis",
      "value": "Sterilisiert"
    },
    {
      "label": "Kühlhinweis / Aufbewahrungshinweis",
      "value": "Bei Raumtemperatur aufbewahren. Nach dem Öffnen nicht in der Dose aufbewahren, im Kühlschrank lagern und rasch konsumieren."
    }
  ],
  "image": {
    "original": "https://image.migros.ch/original/57f93cfaf394322404c624828bd53ea2bca5e53d/sun-queen-max-hav-ananasscheiben.jpg",
    "stack": "https://image.migros.ch/{stack}/57f93cfaf394322404c624828bd53ea2bca5e53d/sun-queen-max-hav-ananasscheiben.jpg"
  },
  "image_transparent": {
    "original": "https://image.migros.ch/original/b7cb2e3c96eff702365ab699de472eb8bb8a9bc6/sun-queen-max-hav-ananasscheiben.png",
    "stack": "https://image.migros.ch/{stack}/b7cb2e3c96eff702365ab699de472eb8bb8a9bc6/sun-queen-max-hav-ananasscheiben.png"
  },
  "internal_features": [
    {
      "label_code": "MISO_aMigos_anzeige",
      "label": "Anzeige aMigos!",
      "values": [
        {
          "value_code": "MISO_aMigos_anzeige_ja",
          "value": "Ja"
        }
      ],
      "category_code": "MISO_CLA_aMigos_Alle",
      "top_fact": false
    },
    {
      "label_code": "MAPI_PRODUCT_KIND",
      "values": [
        {
          "value_code": "HAWA",
          "value": "Handelsware"
        }
      ],
      "category_code": "MAPI_PRODUCT_KIND",
      "top_fact": false
    },
    {
      "label_code": "MAPI_ASSORTMENT_LIST_KIND",
      "values": [
        {
          "value_code": "L",
          "value": "Lieferunterbruch"
        }
      ],
      "category_code": "MAPI_ASSORTMENT_LIST_KIND",
      "top_fact": false
    },
    {
      "label_code": "MAPI_PRODUCT_GROUP",
      "values": [
        {
          "value_code": "11134",
          "value": "FRUCHTKONSERVEN"
        }
      ],
      "category_code": "MAPI_PRODUCT_GROUP",
      "top_fact": false
    }
  ],
  "vat": {
    "id": 2,
    "percentage": 2.5
  },
  "regulated_description": "Ananasscheiben in Ananassaft",
  "links": {
    "migros_ch": {
      "url": "https://produkte.migros.ch/products/152004900000",
      "name": "migros.ch",
      "canonical": "https://produkte.migros.ch/sun-queen-max-hav-ananasscheiben",
      "type": "info",
      "purchasable": false
    },
    "migipedia": {
      "url": "https://migipedia.migros.ch/de/products/152004900000",
      "name": "Migipedia",
      "canonical": "https://produkte.migros.ch/sun-queen-max-hav-ananasscheiben",
      "type": "info",
      "purchasable": false
    },
    "leshop": {
      "url": "https://www.leshop.ch/de/direct/product/4962145",
      "app_url": "leshop:///catalog/article/detail?ean=7613312104897",
      "name": "LeShop.ch",
      "canonical": "https://produkte.migros.ch/sun-queen-max-hav-ananasscheiben",
      "type": "shop",
      "purchasable": true
    }
  },
  "regional_availability": {
    "gmaa": {
      "probability": 13
    },
    "gmbs": {
      "probability": 24
    },
    "gmge": {
      "probability": 28
    },
    "gmlu": {
      "probability": 17
    },
    "gmnf": {
      "probability": 12
    },
    "gmos": {
      "probability": 12
    },
    "gmti": {
      "probability": 16
    },
    "gmvd": {
      "probability": 23
    },
    "gmvs": {
      "probability": 21
    },
    "gmzh": {
      "probability": 13
    }
  },
  "updated_at": "2020-09-16T05:46:49+0200",
  "base_unit": "CU",
  "slugs": {
    "de": "sun-queen-max-hav-ananasscheiben",
    "fr": "sun-queen-max-hav-tranches-dananas",
    "it": "sun-queen-max-hav-fettine-ananas"
  },
  "receipt_text": "Sun Queen MH Ananas",
  "main_supplier": {
    "name": "Samroiyod Corporation Ltd",
    "id": "0010000372"
  },
  "price": {
    "valid_from": "2018-01-29T00:00:00+0100",
    "valid_to": "9999-12-31T23:59:59+0100",
    "currency": "CHF",
    "source": "PriceRepository",
    "item": {
      "price": 1.95,
      "quantity": 1,
      "unit": "CU",
      "varying_quantity": false,
      "display_quantity": "340g"
    },
    "base": {
      "price": 0.57,
      "quantity": 100,
      "unit": "g"
    }
  },
  "retailer": {
    "id": "supermarkt",
    "name": "Supermarkt"
  },
  "ratings": {
    "count_all": 1,
    "average_all": 5
  },
  "data_source": "SAP-X11",
  "origins": {
    "producing_country": "Thailändisches Produkt"
  },
  "ingredients": "Ananas, Ananassaft.",
  "package": {
    "content": 340,
    "content_unit_code": "g",
    "content_unit": "Gramm",
    "net_weight": 0.565,
    "net_weight_unit_code": "kg",
    "net_weight_unit": "Kilogramm",
    "precision": "exact",
    "brutto_weight": 0.641,
    "brutto_weight_unit_code": "kg",
    "brutto_volume": 0.831,
    "brutto_volume_unit_code": "cdm",
    "height": 11.5,
    "length": 8.5,
    "width": 8.5,
    "unit_dimension": "cm",
    "price_comparison_content": 100,
    "size": "340g"
  },
  "package_information": {
    "tu": {
      "brutto_weight": 8,
      "brutto_weight_unit_code": "kg",
      "brutto_volume": 11.017,
      "brutto_volume_unit_code": "cdm",
      "height": 12.2,
      "length": 34.6,
      "width": 26.1,
      "dimension_unit_code": "cm",
      "number_of_base_units": 12
    },
    "cu": {
      "brutto_weight": 0.641,
      "brutto_weight_unit_code": "kg",
      "brutto_volume": 0.831,
      "brutto_volume_unit_code": "cdm",
      "height": 11.5,
      "length": 8.5,
      "width": 8.5,
      "dimension_unit_code": "cm",
      "number_of_base_units": 1
    },
    "lu": {
      "brutto_weight": 817,
      "brutto_weight_unit_code": "kg",
      "brutto_volume": 0,
      "height": 0,
      "length": 120,
      "width": 80,
      "dimension_unit_code": "cm",
      "number_of_base_units": 1188
    }
  },
  "declarations": {
    "food": {
      "features": [
        {
          "label_code": "GDSN_M280_DrainedWeight",
          "label": "Abtropfgewicht",
          "values": [
            {
              "value": "340 g"
            }
          ],
          "category_code": "GDSN",
          "top_fact": false,
          "unit_code": "g",
          "unit": "Gramm",
          "unit_symbol": "g"
        },
        {
          "label_code": "GDSN_M281_NetContent",
          "label": "Nettofüllmenge Wert",
          "values": [
            {
              "value_code": "NUMERIC_565",
              "value": "565",
              "numeric_value": 565
            }
          ],
          "category_code": "GDSN",
          "top_fact": false,
          "unit_code": "g"
        }
      ]
    }
  },
  "reindex_date": "9999-12-31T00:00:00+0100",
  "recipe_ingredient_ids": [
    "14449"
  ],
  "views": [
    "all",
    "browse"
  ]
}